{"levelingUps": [{"types": ["\u87f2", "\u98db\u884c"], "link": "12", "nameZh": "\u5df4\u5927\u8776", "altForm": null, "level": 32}, {"types": ["\u5730\u9762", "\u9f8d"], "link": "329", "nameZh": "\u8d85\u97f3\u6ce2\u5e7c\u87f2", "altForm": null, "level": 28, "child": true}, {"types": ["\u5730\u9762", "\u9f8d"], "link": "330", "nameZh": "\u6c99\u6f20\u873b\u8713", "altForm": null, "level": 28}, {"types": ["\u87f2"], "link": "588", "nameZh": "\u84cb\u84cb\u87f2", "altForm": null, "level": 44, "child": true}, {"types": ["\u87f2", "\u92fc"], "link": "589", "nameZh": "\u9a0e\u58eb\u8778\u725b", "altForm": null, "level": 44}, {"types": ["\u87f2", "\u96fb"], "link": "595", "nameZh": "\u96fb\u96fb\u87f2", "altForm": null, "level": 48, "child": true}, {"types": ["\u87f2", "\u96fb"], "link": "596", "nameZh": "\u96fb\u8718\u86db", "altForm": null, "level": 56}, {"types": ["\u87f2"], "link": "616", "nameZh": "\u5c0f\u5634\u8778", "altForm": null, "level": 44, "child": true}, {"types": ["\u87f2"], "link": "617", "nameZh": "\u654f\u6377\u87f2", "altForm": null, "level": 44}, {"types": ["\u87f2", "\u706b"], "link": "636", "nameZh": "\u71c3\u71d2\u87f2", "altForm": null, "level": 42, "child": true}, {"types": ["\u87f2", "\u706b"], "link": "637", "nameZh": "\u706b\u795e\u86fe", "altForm": null, "level": 42}, {"types": ["\u87f2", "\u92fc"], "link": "649", "nameZh": "\u84cb\u8afe\u8cfd\u514b\u7279", "altForm": null, "level": 56}, {"types": ["\u87f2", "\u92fc"], "link": "649-1", "nameZh": "\u84cb\u8afe\u8cfd\u514b\u7279", "altForm": "\u9583\u96fb\u5361\u5e36", "level": 56}, {"types": ["\u87f2", "\u92fc"], "link": "649-2", "nameZh": "\u84cb\u8afe\u8cfd\u514b\u7279", "altForm": "\u706b\u7130\u5361\u5e36", "level": 56}, {"types": ["\u87f2", "\u92fc"], "link": "649-3", "nameZh": "\u84cb\u8afe\u8cfd\u514b\u7279", "altForm": "\u51b0\u51cd\u5361\u5e36", "level": 56}, {"types": ["\u87f2", "\u92fc"], "link": "649-4", "nameZh": "\u84cb\u8afe\u8cfd\u514b\u7279", "altForm": "\u6c34\u6d41\u5361\u5e36", "level": 56}, {"types": ["\u87f2", "\u96fb"], "link": "738", "nameZh": "\u936c\u8fb2\u70ae\u87f2", "altForm": null, "level": 36}, {"types": ["\u87f2", "\u5996\u7cbe"], "link": "742", "nameZh": "\u840c\u867b", "altForm": null, "level": 48, "child": true}, {"types": ["\u87f2", "\u5996\u7cbe"], "link": "743", "nameZh": "\u8776\u7d50\u840c\u867b", "altForm": null, "level": 56}, {"types": ["\u87f2", "\u683c\u9b25"], "link": "795", "nameZh": "\u8cbb\u6d1b\u7f8e\u8782", "altForm": null, "level": 60}, {"types": ["\u87f2", "\u8d85\u80fd\u529b"], "link": "826", "nameZh": "\u4ee5\u6b50\u8def\u666e", "altForm": null, "level": 28}, {"types": ["\u51b0", "\u87f2"], "link": "873", "nameZh": "\u96ea\u7d68\u86fe", "altForm": null, "level": 32}], "egg": [], "pid": 405, "nameZh": "\u87f2\u9cf4", "nameJp": "\u3080\u3057\u306e\u3055\u3056\u3081\u304d", "nameEn": "Bug Buzz", "type": "\u87f2", "category": "\u7279\u6b8a", "power": 90, "accuracy": 100, "PP": 10, "description": "\u5229\u7528\u632f\u52d5\u7522\u751f\u51fa\u7684\u97f3\u6ce2\u9032\u884c\u653b\u64ca\u3002\u6709\u6642\u6703\u964d\u4f4e\u5c0d\u624b\u7684\u7279\u9632\u3002", "TR": {"pid": 61, "pm": [{"types": ["\u87f2", "\u98db\u884c"], "link": "12", "nameZh": "\u5df4\u5927\u8776", "altForm": null}, {"types": ["\u87f2", "\u98db\u884c"], "link": "123", "nameZh": "\u98db\u5929\u87b3\u8782", "altForm": null, "child": true}, {"types": ["\u8d85\u80fd\u529b"], "link": "151", "nameZh": "\u5922\u5e7b", "altForm": null}, {"types": ["\u87f2", "\u92fc"], "link": "212", "nameZh": "\u5de8\u9257\u87b3\u8782", "altForm": null}, {"types": ["\u87f2", "\u5730\u9762"], "link": "290", "nameZh": "\u571f\u5c45\u5fcd\u58eb", "altForm": null, "child": true}, {"types": ["\u87f2", "\u98db\u884c"], "link": "291", "nameZh": "\u9435\u9762\u5fcd\u8005", "altForm": null}, {"types": ["\u87f2", "\u5e7d\u9748"], "link": "292", "nameZh": "\u812b\u6bbc\u5fcd\u8005", "altForm": null}, {"types": ["\u5730\u9762", "\u9f8d"], "link": "329", "nameZh": "\u8d85\u97f3\u6ce2\u5e7c\u87f2", "altForm": null, "child": true}, {"types": ["\u5730\u9762", "\u9f8d"], "link": "330", "nameZh": "\u6c99\u6f20\u873b\u8713", "altForm": null}, {"types": ["\u87f2", "\u98db\u884c"], "link": "415", "nameZh": "\u4e09\u871c\u8702", "altForm": null, "child": true}, {"types": ["\u87f2", "\u98db\u884c"], "link": "416", "nameZh": "\u8702\u5973\u738b", "altForm": null}, {"types": ["\u6bd2", "\u87f2"], "link": "451", "nameZh": "\u9257\u5c3e\u880d", "altForm": null, "child": true}, {"types": ["\u6bd2", "\u60e1"], "link": "452", "nameZh": "\u9f8d\u738b\u880d", "altForm": null}, {"types": ["\u87f2"], "link": "588", "nameZh": "\u84cb\u84cb\u87f2", "altForm": null, "child": true}, {"types": ["\u87f2", "\u92fc"], "link": "589", "nameZh": "\u9a0e\u58eb\u8778\u725b", "altForm": null}, {"types": ["\u87f2", "\u96fb"], "link": "595", "nameZh": "\u96fb\u96fb\u87f2", "altForm": null, "child": true}, {"types": ["\u87f2", "\u96fb"], "link": "596", "nameZh": "\u96fb\u8718\u86db", "altForm": null}, {"types": ["\u87f2"], "link": "616", "nameZh": "\u5c0f\u5634\u8778", "altForm": null, "child": true}, {"types": ["\u87f2"], "link": "617", "nameZh": "\u654f\u6377\u87f2", "altForm": null}, {"types": ["\u87f2", "\u706b"], "link": "636", "nameZh": "\u71c3\u71d2\u87f2", "altForm": null, "child": true}, {"types": ["\u87f2", "\u706b"], "link": "637", "nameZh": "\u706b\u795e\u86fe", "altForm": null}, {"types": ["\u87f2", "\u92fc"], "link": "649", "nameZh": "\u84cb\u8afe\u8cfd\u514b\u7279", "altForm": null}, {"types": ["\u87f2", "\u92fc"], "link": "649-1", "nameZh": "\u84cb\u8afe\u8cfd\u514b\u7279", "altForm": "\u9583\u96fb\u5361\u5e36"}, {"types": ["\u87f2", "\u92fc"], "link": "649-2", "nameZh": "\u84cb\u8afe\u8cfd\u514b\u7279", "altForm": "\u706b\u7130\u5361\u5e36"}, {"types": ["\u87f2", "\u92fc"], "link": "649-3", "nameZh": "\u84cb\u8afe\u8cfd\u514b\u7279", "altForm": "\u51b0\u51cd\u5361\u5e36"}, {"types": ["\u87f2", "\u92fc"], "link": "649-4", "nameZh": "\u84cb\u8afe\u8cfd\u514b\u7279", "altForm": "\u6c34\u6d41\u5361\u5e36"}, {"types": ["\u87f2", "\u96fb"], "link": "738", "nameZh": "\u936c\u8fb2\u70ae\u87f2", "altForm": null}, {"types": ["\u87f2", "\u5996\u7cbe"], "link": "742", "nameZh": "\u840c\u867b", "altForm": null, "child": true}, {"types": ["\u87f2", "\u5996\u7cbe"], "link": "743", "nameZh": "\u8776\u7d50\u840c\u867b", "altForm": null}, {"types": ["\u6c34", "\u87f2"], "link": "751", "nameZh": "\u6ef4\u86db", "altForm": null, "child": true}, {"types": ["\u6c34", "\u87f2"], "link": "752", "nameZh": "\u6ef4\u86db\u9738", "altForm": null}, {"types": ["\u87f2", "\u6c34"], "link": "767", "nameZh": "\u81bd\u5c0f\u87f2", "altForm": null, "child": true}, {"types": ["\u87f2", "\u6c34"], "link": "768", "nameZh": "\u5177\u7532\u6b66\u8005", "altForm": null}, {"types": ["\u87f2", "\u683c\u9b25"], "link": "795", "nameZh": "\u8cbb\u6d1b\u7f8e\u8782", "altForm": null}, {"types": ["\u87f2", "\u8d85\u80fd\u529b"], "link": "825", "nameZh": "\u5929\u7f69\u87f2", "altForm": null, "child": true}, {"types": ["\u87f2", "\u8d85\u80fd\u529b"], "link": "826", "nameZh": "\u4ee5\u6b50\u8def\u666e", "altForm": null}, {"types": ["\u706b", "\u87f2"], "link": "850", "nameZh": "\u71d2\u706b\u86a3", "altForm": null, "child": true}, {"types": ["\u706b", "\u87f2"], "link": "851", "nameZh": "\u711a\u7130\u86a3", "altForm": null}, {"types": ["\u51b0", "\u87f2"], "link": "872", "nameZh": "\u96ea\u541e\u87f2", "altForm": null, "child": true}, {"types": ["\u51b0", "\u87f2"], "link": "873", "nameZh": "\u96ea\u7d68\u86fe", "altForm": null}]}}